promptbuf/__init__.py
promptbuf-0.1.1.dist-info/METADATA
promptbuf-0.1.1.dist-info/WHEEL
promptbuf-0.1.1.dist-info/top_level.txt
promptbuf-0.1.1.dist-info/RECORD
